GeoMeshPy/vmod.py
geomeshconv-0.0.9.dist-info/DESCRIPTION.rst
geomeshconv-0.0.9.dist-info/METADATA
geomeshconv-0.0.9.dist-info/RECORD
geomeshconv-0.0.9.dist-info/WHEEL
geomeshconv-0.0.9.dist-info/metadata.json
geomeshconv-0.0.9.dist-info/top_level.txt
