Metadata-Version: 2.0
Name: geomeshconv
Version: 0.0.9
Summary: A Python package to convert the geology to in mesh generator (GMSH).
Home-page: https://github.com/Ali1990dashti/GeoMeshPy
Author: Ali Dashti
Author-email: Ali.dashti@kit.edu
License: MIT
Platform: UNKNOWN
Requires-Dist: numpy
Requires-Dist: numpy-indexed
Requires-Dist: pandas
